logviewer/__init__.py
logviewer/admin.py
logviewer/app_settings.py
logviewer/apps.py
logviewer/models.py
logviewer/urls.py
logviewer/views.py
logviewer/migrations/__init__.py
logviewer/static/logviewer/js/logviewer.js
logviewer/templates/logviewer/base.html
logviewer/templates/logviewer/logs.html
logviewer/templatetags/__init__.py
logviewer/templatetags/logviewer_tags.py
django_admin_logviewer-0.1.4.dist-info/LICENSE
django_admin_logviewer-0.1.4.dist-info/METADATA
django_admin_logviewer-0.1.4.dist-info/WHEEL
django_admin_logviewer-0.1.4.dist-info/top_level.txt
django_admin_logviewer-0.1.4.dist-info/RECORD
