Metadata-Version: 2.1
Name: django-admin-logviewer
Version: 0.1.4
Summary: Allows the viewing and download of specific log files in real time directly from the Django admin interface. 
Home-page: https://github.com/morlandi/django-logviewer
Author: Mario Orlandi
Author-email: morlandi@brainstorm.it
License: BSD
Platform: OS Independent
Classifier: Development Status :: 5 - Production/Stable
Classifier: Framework :: Django
Classifier: Intended Audience :: Developers
Classifier: License :: OSI Approved :: BSD License
Classifier: Operating System :: OS Independent
Classifier: Programming Language :: Python
Classifier: Topic :: Internet :: WWW/HTTP
Classifier: Framework :: Django
Classifier: Framework :: Django :: 4.0
Classifier: Programming Language :: Python :: 3.8
